ipman/errors.py
ipman/ipman.py
ipman/iptoolz.py
ipman-1.1.1.1.0.dist-info/LICENSE.txt
ipman-1.1.1.1.0.dist-info/METADATA
ipman-1.1.1.1.0.dist-info/WHEEL
ipman-1.1.1.1.0.dist-info/top_level.txt
ipman-1.1.1.1.0.dist-info/RECORD
