Metadata-Version: 2.1
Name: ipman
Version: 1.1.1.1.0
Summary: ipman is a high-level core python package for Internet Protocol(IP) manipulations.
Home-page: https://github.com/moriire/ipman
Download-URL: https://github.com/moriire/ipman/archive/v_110.tar.gz
Author: Mobolaji Abdulsalam
Author-email: ibraheemabdulsalam@gmail.com
License: MIT
Keywords: IPMan is a high-level core python package for Internet Protocol(IP) manipulations.
Classifier: Development Status :: 3 - Alpha
Classifier: Intended Audience :: Developers
Classifier: Topic :: Software Development :: Build Tools
Classifier: License :: OSI Approved :: MIT License
Classifier: Programming Language :: Python :: 3.10
Requires-Python: >=3.10
License-File: LICENSE.txt
